tiny_chat/__init__.py
tiny_chat/agents/__init__.py
tiny_chat/agents/base_agent.py
tiny_chat/agents/human_agent.py
tiny_chat/agents/llm_agent.py
tiny_chat/config.py
tiny_chat/data/__init__.py
tiny_chat/data/loader.py
tiny_chat/data/samplers/__init__.py
tiny_chat/data/samplers/base_sampler.py
tiny_chat/data/samplers/constraint_sampler.py
tiny_chat/data/samplers/uniform_sampler.py
tiny_chat/envs/__init__.py
tiny_chat/envs/base.py
tiny_chat/envs/tinychat_env.py
tiny_chat/evaluator/__init__.py
tiny_chat/evaluator/base.py
tiny_chat/evaluator/dimensions.py
tiny_chat/evaluator/llm_evaluator.py
tiny_chat/evaluator/manager.py
tiny_chat/evaluator/rule_based.py
tiny_chat/evaluator/utils.py
tiny_chat/messages/__init__.py
tiny_chat/messages/messages.py
tiny_chat/profiles/__init__.py
tiny_chat/profiles/agent_profile.py
tiny_chat/profiles/enviroment_profile.py
tiny_chat/profiles/relationship_profile.py
tiny_chat/providers/__init__.py
tiny_chat/providers/base.py
tiny_chat/providers/factory.py
tiny_chat/providers/generate.py
tiny_chat/providers/litellm_provider.py
tiny_chat/providers/output_parsers.py
tiny_chat/providers/utils.py
tiny_chat/providers/workflow_provider.py
tiny_chat/server/README.md
tiny_chat/server/__init__.py
tiny_chat/server/api.py
tiny_chat/server/cli.py
tiny_chat/server/core.py
tiny_chat/utils/__init__.py
tiny_chat/utils/cli.py
tiny_chat/utils/error_handler.py
tiny_chat/utils/format_handler.py
tiny_chat/utils/json_saver.py
tiny_chat/utils/logger.py
tiny_chat/utils/logs.py
tiny_chat/utils/template.py
tiny_chat-0.0.1.dist-info/METADATA
tiny_chat-0.0.1.dist-info/WHEEL
tiny_chat-0.0.1.dist-info/licenses/LICENSE
tiny_chat-0.0.1.dist-info/RECORD
