Metadata-Version: 2.4
Name: tiny-chat
Version: 0.0.1
Summary: A lightweight platform for realistic social simulations
License: MIT
License-File: LICENSE
Author: Yining Zhao
Requires-Python: >=3.10,<3.13
Classifier: License :: OSI Approved :: MIT License
Classifier: Programming Language :: Python :: 3
Classifier: Programming Language :: Python :: 3.10
Classifier: Programming Language :: Python :: 3.11
Classifier: Programming Language :: Python :: 3.12
Requires-Dist: asyncio (>=3.4.3,<4.0.0)
Requires-Dist: beartype (>=0.17.1,<0.18.0)
Requires-Dist: datasets (>=4.0.0,<5.0.0)
Requires-Dist: gymnasium (>=0.29.0,<0.30.0)
Requires-Dist: json-repair (>=0.48.0,<0.49.0)
Requires-Dist: litellm (>=1.75.0,<2.0.0)
Requires-Dist: mypy (>=1.17.1,<2.0.0)
Requires-Dist: openai (>=1.12.0,<2.0.0)
Requires-Dist: pettingzoo (>=1.24.0,<2.0.0)
Requires-Dist: pydantic (>=2.8.2,<3.0.0)
Requires-Dist: rich (>=14.1.0,<15.0.0)
Requires-Dist: typing-extensions (>=4.9.0,<5.0.0)
